<?xml version="1.0" encoding="utf-8" standalone="yes"?>
<PACKAGE>
  <DELETE>
    <offers />
    <pictures />
  </DELETE>
  <offer>
    <signature>230/6093/OGS</signature>
    <parameters>
      <p id="1">230/6093/OGS</p>
      <p id="2">Biuro Nieruchomości DAN-DOM</p>
      <p id="3">2026-06-12 09:20:25.0594</p>
      <p id="5">2026-01-14 11:07:51.0587</p>
      <p id="10">260000.0000</p>
      <p id="13">266.6700</p>
      <p id="18">BUDOWLANA</p>
      <p id="26">AKTUALNA</p>
      <p id="36">DZIAŁKA</p>
      <p id="39">WODA MIEJSKA W DRODZE, KAN. MIEJSKA W DRODZE</p>
      <p id="41">ASFALTOWA</p>
      <p id="43">SPRZEDAŻ</p>
      <p id="45">WIELKOPOLSKIE</p>
      <p id="46">WĄGROWIECKI</p>
      <p id="47">WĄGROWIEC</p>
      <p id="48">WĄGROWIEC</p>
      <p id="49"></p>
      <p id="51">0.0000</p>
      <p id="52"></p>
      <p id="53"></p>
      <p id="54">PŁASKIE</p>
      <p id="60">POLSKA</p>
      <p id="61">975.0000</p>
      <p id="89"></p>
      <p id="93">61126.0000</p>
      <p id="94">70512.0000</p>
      <p id="141">PLN</p>
      <p id="155">GAZ W DRODZE, PRĄD W DRODZE</p>
      <p id="170">501-769-166</p>
      <p id="171">dan-dom@wp.pl</p>
      <p id="172">577</p>
      <p id="174">34716.0000</p>
      <p id="201"></p>
      <p id="202"></p>
      <p id="220">WTÓRNY</p>
      <p id="300">Wierzbowa</p>
      <p id="305">Danuta Majchrzak</p>
      <p id="307">NIE</p>
      <p id="340"></p>
      <p id="341"></p>
      <p id="342"></p>
      <p id="343"></p>
      <p id="344"></p>
      <p id="345"></p>
      <p id="349">NIE</p>
      <p id="489">TAK</p>
      <p id="491">Działka pod zabudowę Wągrowiec ul. Wierzbowa</p>
      <p id="492">NIE</p>
    </parameters>
    <pictures>
      <picture>
        <unique>113224319.jpg</unique>
        <status>1</status>
        <weight>1</weight>
        <description />
      </picture>
      <picture>
        <unique>110171876.jpg</unique>
        <status>0</status>
        <weight>2</weight>
        <description />
      </picture>
      <picture>
        <unique>110171877.jpg</unique>
        <status>0</status>
        <weight>3</weight>
        <description />
      </picture>
      <picture>
        <unique>110171878.jpg</unique>
        <status>0</status>
        <weight>4</weight>
        <description />
      </picture>
      <picture>
        <unique>110171879.jpg</unique>
        <status>0</status>
        <weight>5</weight>
        <description />
      </picture>
      <picture>
        <unique>110171881.jpg</unique>
        <status>0</status>
        <weight>6</weight>
        <description />
      </picture>
      <picture>
        <unique>110171882.jpg</unique>
        <status>0</status>
        <weight>7</weight>
        <description />
      </picture>
    </pictures>
    <description>REZERWACJA OFERTY!!!!!!!!!!!!!!!!&lt;br/&gt;&lt;br/&gt;&lt;br/&gt;Polecamy Państwu na sprzedaż działkę położoną w spokojnej części miasta, z dobrym dojazdem do centrum, która znajduje się przy ulicy Wierzbowej w Wągrowcu.&lt;br/&gt;Oferta unikatowa ze względu na lokalizację i małą dostępność działek w Wągrowcu.&lt;br/&gt;&lt;br/&gt;Współpraca z nami - kupując tę nieruchomość, zyskujesz kompleksową opiekę prawną oraz pomoc w uzyskaniu finansowania.&lt;br/&gt;Informujemy, że usługa pośrednictwa jest płatna zgodnie z regulaminem biura.&lt;br/&gt;&lt;br/&gt;Działka nie jest objęta planem zagospodarowania przestrzennego, lecz posiada nową wydaną w 2025 roku decyzję o warunkach zabudowy - zabudowa mieszkaniowa jednorodzinna (warunki bezterminowe).&lt;br/&gt;&lt;br/&gt;Wraz z działką, w podanej cenie, zbywany jest udział 1/2 części w działce zapewniającej dostęp do drogi publicznej. &lt;br/&gt;&lt;br/&gt;Pełne uzbrojenie w głównej drodze asfaltowej: prąd, woda, kanalizacja, oraz gaz.&lt;br/&gt;&lt;br/&gt;Posesja niemal cała ogrodzona.&lt;br/&gt;&lt;br/&gt;Sąsiedztwo stanowią domy jednorodzinne. W najbliższej okolicy znajduje się market, szkoła. Doskonałe połączenie komunikacyjne, zarówno z centrum miasta jak i z dojazdem do obwodnicy. &lt;br/&gt;&lt;br/&gt;W ofercie posiadamy na sprzedaż działkę sąsiednią - możliwość nabycia dwóch nieruchomości co uczyni teren jeszcze bardziej atrakcyjnym ze strefą prywatną.&lt;br/&gt;&lt;br/&gt;Zachęcamy Państwa do kontaktu i prezentacji.&lt;br/&gt;&lt;br/&gt;W razie dodatkowych pytań służymy pomocą.&lt;br/&gt;&lt;br/&gt;Osoba prowadząca ofertę: Marta Janusz tel. 519 110 078, oraz Danuta Majchrzak 501 769 166.&lt;br/&gt;&lt;br/&gt;Zachęcamy do korzystania z naszego profilu na Facebook:&lt;br/&gt;https://www.facebook.com/biurodandom&lt;br/&gt;

</description>
  </offer>
  <offer>
    <signature>232/6093/OGS</signature>
    <parameters>
      <p id="1">232/6093/OGS</p>
      <p id="2">Biuro Nieruchomości DAN-DOM</p>
      <p id="3">2026-06-12 09:20:36.0054</p>
      <p id="5">2026-03-11 18:39:58.0127</p>
      <p id="10">360000.0000</p>
      <p id="13">187.0100</p>
      <p id="18">BUDOWLANA</p>
      <p id="26">AKTUALNA</p>
      <p id="36">DZIAŁKA</p>
      <p id="39">WODA MIEJSKA W DRODZE, SZAMBO SZCZELNE</p>
      <p id="41">GRUNTOWA</p>
      <p id="43">SPRZEDAŻ</p>
      <p id="44">Tereny zabudowy mieszkaniowej</p>
      <p id="45">WIELKOPOLSKIE</p>
      <p id="46">WĄGROWIECKI</p>
      <p id="47">WĄGROWIEC</p>
      <p id="48">WIATROWO</p>
      <p id="49">WIATROWO-LAS</p>
      <p id="51">0.0000</p>
      <p id="52"></p>
      <p id="53"></p>
      <p id="54">PŁASKIE</p>
      <p id="55">PROSTOKĄT</p>
      <p id="60">POLSKA</p>
      <p id="61">1925.0000</p>
      <p id="66">WŁASNOŚĆ</p>
      <p id="89"></p>
      <p id="93">84636.0000</p>
      <p id="94">97632.0000</p>
      <p id="141">PLN</p>
      <p id="155">BRAK GAZU, PRĄD</p>
      <p id="170">501-769-166</p>
      <p id="171">dan-dom@wp.pl</p>
      <p id="172">577</p>
      <p id="174">34716.0000</p>
      <p id="201"></p>
      <p id="202"></p>
      <p id="220">WTÓRNY</p>
      <p id="305">Danuta Majchrzak</p>
      <p id="307">NIE</p>
      <p id="340"></p>
      <p id="341"></p>
      <p id="342"></p>
      <p id="343"></p>
      <p id="344"></p>
      <p id="345"></p>
      <p id="349">NIE</p>
      <p id="489">TAK</p>
      <p id="491">Piękna działka Wiatrowo Las z pozwoleniem</p>
      <p id="492">NIE</p>
    </parameters>
    <pictures>
      <picture>
        <unique>111234263.jpg</unique>
        <status>1</status>
        <weight>1</weight>
        <description />
      </picture>
      <picture>
        <unique>111234485.jpg</unique>
        <status>0</status>
        <weight>2</weight>
        <description />
      </picture>
      <picture>
        <unique>111234520.jpg</unique>
        <status>0</status>
        <weight>3</weight>
        <description />
      </picture>
      <picture>
        <unique>111234490.jpg</unique>
        <status>0</status>
        <weight>4</weight>
        <description />
      </picture>
      <picture>
        <unique>111234494.jpg</unique>
        <status>0</status>
        <weight>5</weight>
        <description />
      </picture>
      <picture>
        <unique>111234495.jpg</unique>
        <status>0</status>
        <weight>6</weight>
        <description />
      </picture>
      <picture>
        <unique>111234267.jpg</unique>
        <status>0</status>
        <weight>7</weight>
        <description />
      </picture>
      <picture>
        <unique>111234268.jpg</unique>
        <status>0</status>
        <weight>8</weight>
        <description />
      </picture>
      <picture>
        <unique>111234269.jpg</unique>
        <status>0</status>
        <weight>9</weight>
        <description />
      </picture>
      <picture>
        <unique>111234753.jpg</unique>
        <status>0</status>
        <weight>10</weight>
        <description />
      </picture>
      <picture>
        <unique>111234754.jpg</unique>
        <status>0</status>
        <weight>11</weight>
        <description />
      </picture>
    </pictures>
    <description>Oferujemy wyjątkową działkę pod lasem z pozwoleniem na budowę – harmonia natury i bliskość Wągrowca.&lt;br/&gt;NAJWIĘKSZY ATUT:&lt;br/&gt;Działka o niepowtarzalnym charakterze, położona bezpośrednio przy ścianie lasu (własność Lasy Państwowe). To idealne miejsce dla osób szukających prywatności, ciszy i kontaktu z naturą, nie rezygnując przy tym z udogodnień, jakie daje sąsiedztwo miasta.&lt;br/&gt;&lt;br/&gt;Współpraca z nami - kupując tę nieruchomość, zyskujesz kompleksową opiekę prawną oraz pomoc w uzyskaniu finansowania.&lt;br/&gt;Informujemy, że usługa pośrednictwa jest płatna zgodnie z regulaminem biura.&lt;br/&gt;&lt;br/&gt;PODSTAWOWE INFORMACJE:&lt;br/&gt;Lokalizacja: Wiatrowo Las – tylko 3 km od Wągrowca&lt;br/&gt;Powierzchnia: 1925 m²&lt;br/&gt;Cena: 360 000 zł&lt;br/&gt;&lt;br/&gt;CHARAKTERYSTYKA TERENU:&lt;br/&gt;Sąsiedztwo: bezpośrednia granica z lasem, brak możliwości zabudowy za Twoim ogrodem – gwarancja widoku!&lt;br/&gt;Ukształtowanie: teren suchy, płaski, z naturalnym leśnym starodrzewem na granicy, oraz samosiejkami &lt;br/&gt;Prywatność: Kameralne położenie, niska intensywność zabudowy w sąsiedztwie&lt;br/&gt;Teren ogrodzony, pozostaje do zamontowania brama wjazdowa i furtka&lt;br/&gt;Dojazd do samej działki drogą polną, dogodny dojazd drogą asfaltową do miasta powiatowego  &lt;br/&gt;&lt;br/&gt;POTENCJAŁ ZABUDOWY:&lt;br/&gt;Status: obowiązujący miejscowy plan - przeznaczenie pod budownictwo jednorodzinne.&lt;br/&gt;Wydane pozwolenie na budowę budynku mieszkalnego w technologi szkieletowej i garażu wraz z dokumentacją budowlaną (projekt w załączeniu do ogłoszenia)&lt;br/&gt;Media:&lt;br/&gt;- rozprowadzenie i podłączenie wody i kanalizacji w całości po działce&lt;br/&gt;- rozprowadzenie i podłączenie prądu w całości po działce wraz z okablowaniem tzw skrętką pod bramy domofony&lt;br/&gt;- szambo z podłączeniami&lt;br/&gt;&lt;br/&gt;DLACZEGO WARTO?&lt;br/&gt;Nietuzinkowy klimat: Budzisz się przy śpiewie ptaków i szumie drzew.&lt;br/&gt;Logistyka: Dojazd do miasta zajmuje zaledwie kilka minut. W pobliżu: ścieżka rowerowa, 5 km do jeziora,&lt;br/&gt;&lt;br/&gt;KONTAKT&lt;br/&gt;Imię i nazwisko: Marta Janusz, licencja PFRN nr 28634&lt;br/&gt;Telefon: 519 110 078&lt;br/&gt;Imię i nazwisko: Danuta Majchrzak, licencja PFRN nr 577&lt;br/&gt;Telefon: 501 769 166&lt;br/&gt;&lt;br/&gt;Serdecznie zachęcamy do oglądania!&lt;br/&gt;W razie dodatkowych pytań służymy pomocą, również przy uzyskaniu kredytu na zakup.&lt;br/&gt;&lt;br/&gt;Zachęcamy do korzystania z naszego profilu na Facebook:&lt;br/&gt;https://www.facebook.com/biurodandom

</description>
  </offer>
</PACKAGE>